icloud_homie/__init__.py
icloud_homie/icloud_account.py
icloud_homie/homie_device/__init__.py
icloud_homie/homie_device/device_icloud_account.py
icloud_homie/homie_device/device_icloud_device.py
iCloud_Homie_4-0.1.1.dist-info/LICENSE
iCloud_Homie_4-0.1.1.dist-info/METADATA
iCloud_Homie_4-0.1.1.dist-info/WHEEL
iCloud_Homie_4-0.1.1.dist-info/top_level.txt
iCloud_Homie_4-0.1.1.dist-info/RECORD
