Metadata-Version: 2.1
Name: iCloud-Homie-4
Version: 0.1.1
Summary: Homie 4 for iCloud Devices
Home-page: https://github.com/mjcumming/iCloud-Homie
Author: Michael Cumming
Author-email: mike@4831.com
License: UNKNOWN
Keywords: HOMIE,MQTT,iCloud,iPhone
Platform: UNKNOWN
Classifier: Programming Language :: Python :: 3
Classifier: License :: OSI Approved :: MIT License
Classifier: Operating System :: OS Independent
Requires-Dist: Homie4 (>=0.2.7)
Requires-Dist: pyicloud (>=0.9.2)
Requires-Dist: pyyaml
